cf_orange/__init__.py
cf_orange/interaction_views.py
cf_orange/library.py
cf_orange/odt_converters.py
cf_orange/settings.py
cf_orange/urls.py
cf_orange/views.py
cf_orange/visualization_views.py
cf_orange/lib/__init__.py
cf_orange/lib/clustering.py
cf_orange/lib/interval_discretizer.py
cf_orange/lib/learners.py
cf_orange/lib/scores.py
cf_orange/lib/table_processing.py
cf_orange/package_data/categories/2c4c8f68-33db-411c-a8ce-176096349eba.json
cf_orange/package_data/categories/5723a5b8-8c18-4b1f-9398-e93828556c3c.json
cf_orange/package_data/categories/583debcb-5041-46b3-b464-e21875896710.json
cf_orange/package_data/categories/81efce93-b6c5-4270-bde9-ec946a394b10.json
cf_orange/package_data/categories/8b90267f-c82d-4b62-bee3-66184f4db931.json
cf_orange/package_data/categories/aa3ed779-1e0b-4c6b-883e-24d85b9a6009.json
cf_orange/package_data/categories/d0e46009-46b3-43ed-bff0-5fc986ff6b34.json
cf_orange/package_data/categories/d13c01e6-675f-4c48-a211-b24af72229b0.json
cf_orange/package_data/widgets/00e860b0-d62d-4e1d-8f58-0a1755c0f0e1.json
cf_orange/package_data/widgets/0ce778a2-b40c-45f1-8383-9327b18fc661.json
cf_orange/package_data/widgets/0d32c3a7-1f94-4414-92f0-bb81a9152636.json
cf_orange/package_data/widgets/0e3f39fd-3807-49d5-aab5-4ae441cd9f75.json
cf_orange/package_data/widgets/0e9514ce-914a-4dd0-9952-9cd14877c427.json
cf_orange/package_data/widgets/12b0d57d-1cbc-4e9d-8087-2dcd8ced2a27.json
cf_orange/package_data/widgets/1781ee2a-f353-42b4-96d4-3379329c984e.json
cf_orange/package_data/widgets/2039c5fe-48a1-426c-b418-f0a16fdf1b18.json
cf_orange/package_data/widgets/2299e615-4d72-4db7-9b32-3566b903c749.json
cf_orange/package_data/widgets/29b5871f-1829-4af6-8463-c6515e2010c6.json
cf_orange/package_data/widgets/39809f9a-3742-4ca0-908a-1d8a041261af.json
cf_orange/package_data/widgets/39e85968-5f6e-4ac7-802b-5260b406e123.json
cf_orange/package_data/widgets/4c603285-3aa7-4b55-8d57-cc8285e212c2.json
cf_orange-0.2.dist-info/DESCRIPTION.rst
cf_orange-0.2.dist-info/METADATA
cf_orange-0.2.dist-info/RECORD
cf_orange-0.2.dist-info/WHEEL
cf_orange-0.2.dist-info/metadata.json
cf_orange-0.2.dist-info/top_level.txt
