Metadata-Version: 2.0
Name: cf-orange
Version: 0.2
Summary: Package providing Orange widgets for ClowdFlows 2.0
Home-page: https://github.com/xflows/cf_orange
Author: Anze Vavpetic
Author-email: UNKNOWN
License: MIT License
Platform: UNKNOWN
Classifier: Development Status :: 5 - Production/Stable
Classifier: Intended Audience :: Developers
Classifier: Intended Audience :: Science/Research
Requires-Dist: Orange3 (==3.7.0)
Requires-Dist: liac-arff
